SATELLiTES/SATELLiTES.py
SATELLiTES/SATELLiTES_bg01.png
SATELLiTES/SATELLiTES_bg02.png
SATELLiTES/SATELLiTES_enumeration.py
SATELLiTES/SATELLiTES_favicon.png
SATELLiTES/SATELLiTES_gui.py
SATELLiTES/SATELLiTES_header.png
SATELLiTES/SATELLiTES_header_hd.png
SATELLiTES/SATELLiTES_style.css
SATELLiTES/SATELLiTES_tabs_2reagents.py
SATELLiTES/SATELLiTES_tabs_3reagents.py
SATELLiTES/__init__.py
SATELLiTES_SBDD-1.0.11.dist-info/LICENSE
SATELLiTES_SBDD-1.0.11.dist-info/METADATA
SATELLiTES_SBDD-1.0.11.dist-info/WHEEL
SATELLiTES_SBDD-1.0.11.dist-info/entry_points.txt
SATELLiTES_SBDD-1.0.11.dist-info/top_level.txt
SATELLiTES_SBDD-1.0.11.dist-info/RECORD
