Metadata-Version: 2.1
Name: SATELLiTES-SBDD
Version: 1.0.11
Summary: SATELLiTES - Take your synthon-based ligand discovery to infinity and beyond
Author-email: Corentin BEDART <corentin.bedart@univ-lille.fr>
Project-URL: Homepage, https://github.com/cbedart/SATELLiTES
Project-URL: Issues, https://github.com/cbedart/SATELLiTES/issues
Project-URL: Documentation, https://readthedocs.org
Classifier: Programming Language :: Python :: 3
Classifier: License :: OSI Approved :: MIT License
Classifier: Operating System :: OS Independent
Classifier: Operating System :: Microsoft :: Windows
Classifier: Operating System :: MacOS
Classifier: Operating System :: POSIX
Requires-Python: >=3.10
License-File: LICENSE
Requires-Dist: rdkit
Requires-Dist: PyQt6
Requires-Dist: pandas
Requires-Dist: numpy (<2)
